gtp/__init__.py
gtp-0.2.dist-info/DESCRIPTION.rst
gtp-0.2.dist-info/METADATA
gtp-0.2.dist-info/RECORD
gtp-0.2.dist-info/WHEEL
gtp-0.2.dist-info/metadata.json
gtp-0.2.dist-info/top_level.txt
