Metadata-Version: 2.0
Name: gtp
Version: 0.2
Summary: A library to communicate with instances of GNU Go via stdin/stdout or sockets.
Home-page: https://github.com/CodeReclaimers/gtp
Author: CodeReclaimers, LLC
Author-email: alan@codereclaimers.com
License: MIT
Platform: UNKNOWN
